th_preprocessor/__init__.py
th_preprocessor/data.py
th_preprocessor/preprocess.py
th_simple_preprocessor-0.10.1.dist-info/LICENSE
th_simple_preprocessor-0.10.1.dist-info/METADATA
th_simple_preprocessor-0.10.1.dist-info/WHEEL
th_simple_preprocessor-0.10.1.dist-info/top_level.txt
th_simple_preprocessor-0.10.1.dist-info/RECORD
