Metadata-Version: 2.1
Name: th-simple-preprocessor
Version: 0.10.1
Summary: Simple Thai Preprocess Functions
Home-page: https://github.com/wisesight/th-simple-preprocessor
Author: WISESIGHT Product Development
Author-email: tequila@wisesight.com
Classifier: Programming Language :: Python :: 3
Classifier: License :: OSI Approved :: Apache Software License
Classifier: Natural Language :: Thai
Classifier: Topic :: Scientific/Engineering
Classifier: Topic :: Text Processing
Classifier: Topic :: Text Processing :: General
Classifier: Topic :: Text Processing :: Linguistic
Requires-Python: >=3.7
License-File: LICENSE
Requires-Dist: emoji
